{
  "day": [
    {
      "date": "2013-10-10",
      "slot": [
        {
          "start": "23:00",
          "end": "00:00",
          "title": "Entrada al evento",
          "meta": "UPC Campus Nord"
        }
       ]
    },
    {
      "date": "2013-10-11",
      "slot": [
        {
          "start": "00:00",
          "end": "01:00",
          "title": "Inauguración y Keynote",
          "meta": "UPC Campus Nord"
        },
        {
          "start": "05:00",
          "end": "06:00",
          "title": "Tiempo para comer",
          "meta": "UPC Campus Nord"
        },
        {
          "start": "09:00",
          "end": "09:15",
          "title": "Cierre en la UPC",
          "meta": "UPC Campus Nord"
        },
        {
          "start": "11:00",
          "end": "16:00",
          "title": "Clausura",
          "meta": "Mobile World Centre"
        }
      ]
    }
  ]
}
